gseapy/__init__.py
gseapy/__main__.py
gseapy/algorithm.py
gseapy/base.py
gseapy/biomart.py
gseapy/enrichr.py
gseapy/gse.cp312-win32.pyd
gseapy/gsea.py
gseapy/gsva.py
gseapy/msigdb.py
gseapy/parser.py
gseapy/plot.py
gseapy/scipalette.py
gseapy/ssgsea.py
gseapy/stats.py
gseapy/utils.py
gseapy/data/palette.json
gseapy-1.1.11.dist-info/licenses/LICENSE
gseapy-1.1.11.dist-info/METADATA
gseapy-1.1.11.dist-info/WHEEL
gseapy-1.1.11.dist-info/entry_points.txt
gseapy-1.1.11.dist-info/top_level.txt
gseapy-1.1.11.dist-info/RECORD
