Metadata-Version: 2.4
Name: gseapy
Version: 1.1.11
Summary: Gene Set Enrichment Analysis in Python
Home-page: https://github.com/zqfang/gseapy
Download-URL: https://github.com/zqfang/gseapy
Author: Zhuoqing Fang
Author-email: fzq518@gmail.com
License: MIT
Project-URL: Documentation, https://gseapy.readthedocs.io/en/latest/
Project-URL: Source, https://github.com/zqfang/GSEApy
Project-URL: Tracker, https://github.com/zqfang/GSEApy/issues
Keywords: Gene Ontology,GO,Biology,Enrichment,Bioinformatics,Computational Biology
Classifier: Development Status :: 4 - Beta
Classifier: Intended Audience :: Science/Research
Classifier: License :: OSI Approved :: MIT License
Classifier: Programming Language :: Python :: 3
Classifier: Operating System :: MacOS :: MacOS X
Classifier: Operating System :: Microsoft :: Windows
Classifier: Operating System :: POSIX
Classifier: Topic :: Scientific/Engineering :: Bio-Informatics
Classifier: Topic :: Software Development :: Libraries
Requires-Python: >=3.7
License-File: LICENSE
Requires-Dist: numpy>=1.13.0
Requires-Dist: scipy
Requires-Dist: pandas
Requires-Dist: matplotlib>=2.2
Requires-Dist: requests
Dynamic: author
Dynamic: author-email
Dynamic: classifier
Dynamic: description
Dynamic: description-content-type
Dynamic: download-url
Dynamic: home-page
Dynamic: keywords
Dynamic: license
Dynamic: license-file
Dynamic: project-url
Dynamic: requires-dist
Dynamic: requires-python
Dynamic: summary
